{
 "custom_fields": [], 
 "custom_perms": [], 
 "doctype": "Leave Allocation", 
 "property_setters": [
  {
   "_assign": null, 
   "_comments": null, 
   "_liked_by": null, 
   "_user_tags": null, 
   "creation": "2019-03-12 12:30:36.080036", 
   "default_value": null, 
   "doc_type": "Leave Allocation", 
   "docstatus": 0, 
   "doctype_or_field": "DocField", 
   "field_name": "total_leaves_allocated", 
   "idx": 0, 
   "modified": "2019-03-12 12:30:36.080036", 
   "modified_by": "test@test.com", 
   "name": "Leave Allocation-total_leaves_allocated-in_list_view", 
   "owner": "test@test.com", 
   "parent": null, 
   "parentfield": null, 
   "parenttype": null, 
   "property": "in_list_view", 
   "property_type": "Check", 
   "value": "1"
  }, 
  {
   "_assign": null, 
   "_comments": null, 
   "_liked_by": null, 
   "_user_tags": null, 
   "creation": "2019-03-12 12:30:36.062929", 
   "default_value": null, 
   "doc_type": "Leave Allocation", 
   "docstatus": 0, 
   "doctype_or_field": "DocType", 
   "field_name": null, 
   "idx": 0, 
   "modified": "2019-03-12 12:30:36.062929", 
   "modified_by": "test@test.com", 
   "name": "Leave Allocation-read_only_onload", 
   "owner": "test@test.com", 
   "parent": null, 
   "parentfield": null, 
   "parenttype": null, 
   "property": "read_only_onload", 
   "property_type": "Check", 
   "value": null
  }, 
  {
   "_assign": null, 
   "_comments": null, 
   "_liked_by": null, 
   "_user_tags": null, 
   "creation": "2019-03-12 12:29:30.680907", 
   "default_value": null, 
   "doc_type": "Leave Allocation", 
   "docstatus": 0, 
   "doctype_or_field": "DocType", 
   "field_name": null, 
   "idx": 0, 
   "modified": "2019-03-12 12:29:30.680907", 
   "modified_by": "test@test.com", 
   "name": "Leave Allocation-title_field", 
   "owner": "test@test.com", 
   "parent": null, 
   "parentfield": null, 
   "parenttype": null, 
   "property": "title_field", 
   "property_type": "Data", 
   "value": "employee_name"
  }, 
  {
   "_assign": null, 
   "_comments": null, 
   "_liked_by": null, 
   "_user_tags": null, 
   "creation": "2019-02-18 18:21:55.168267", 
   "default_value": null, 
   "doc_type": "Leave Allocation", 
   "docstatus": 0, 
   "doctype_or_field": "DocField", 
   "field_name": "naming_series", 
   "idx": 0, 
   "modified": "2019-02-18 18:21:55.168267", 
   "modified_by": "Administrator", 
   "name": "Leave Allocation-naming_series-options", 
   "owner": "Administrator", 
   "parent": null, 
   "parentfield": null, 
   "parenttype": null, 
   "property": "options", 
   "property_type": "Text", 
   "value": "HR-LAL-.YYYY.-"
  }
 ], 
 "sync_on_migrate": 1
}